clivid/__init__.py
clivid/cli.py
clivid/main.py
clivid/tasks/__init__.py
clivid/tasks/compress_video.py
clivid/tasks/convert_video.py
clivid/tasks/extract_audio.py
clivid/tasks/extract_audio_segment.py
clivid/tasks/list_videos.py
clivid/tasks/merge_videos.py
clivid/tasks/multi_step.py
clivid/tasks/replace_audio.py
clivid/tasks/rotate_video.py
clivid/tasks/simple_resize.py
clivid/tasks/simple_trim.py
clivid/tasks/split_video.py
clivid/tasks/video_info.py
clivid-1.0.4.dist-info/licenses/LICENSE
clivid-1.0.4.dist-info/METADATA
clivid-1.0.4.dist-info/WHEEL
clivid-1.0.4.dist-info/entry_points.txt
clivid-1.0.4.dist-info/top_level.txt
clivid-1.0.4.dist-info/RECORD
